Metadata-Version: 2.1
Name: icdepend
Version: 0.0.0
Summary: test for name
Home-page: https://github.com/yeungchie/icdepend
Author: YEUNGCHIE
Keywords: icdepend,linux
Classifier: Development Status :: 3 - Alpha
Classifier: Intended Audience :: Developers
Classifier: Programming Language :: Python :: 3
Classifier: Programming Language :: Python :: 3.7
Classifier: Programming Language :: Python :: 3.8
Classifier: Programming Language :: Python :: 3.12
Classifier: License :: OSI Approved :: GNU Affero General Public License v3
Classifier: Operating System :: Unix
Requires-Python: >=3.7
